cptpy/__init__.py
cptpy/cpt.py
cptpy/cptu.py
cptpy-0.1.0a0.dist-info/LICENSE.md
cptpy-0.1.0a0.dist-info/METADATA
cptpy-0.1.0a0.dist-info/WHEEL
cptpy-0.1.0a0.dist-info/top_level.txt
cptpy-0.1.0a0.dist-info/RECORD
